ata_db_models/__init__.py
ata_db_models/db_init_stages/_0_init_db.py
ata_db_models/db_init_stages/_1_add_pipeline_1.py
ata_db_models/db_init_stages/_2_add_readonly_user.py
ata_db_models/db_init_stages/_3_add_api.py
ata_db_models/db_init_stages/_4_update_api.py
ata_db_models/db_init_stages/_5_update_readonly_user.py
ata_db_models/db_init_stages/_6_update_api_user.py
ata_db_models/db_init_stages/__init__.py
ata_db_models/helpers.py
ata_db_models/models.py
ata_db_models-0.0.19.dist-info/LICENSE
ata_db_models-0.0.19.dist-info/METADATA
ata_db_models-0.0.19.dist-info/WHEEL
ata_db_models-0.0.19.dist-info/RECORD
