Metadata-Version: 2.1
Name: ata-db-models
Version: 0.0.19
Summary: Database models and migrations for Automating the Ask.
Home-page: https://github.com/LocalAtBrown/ata-models
Author: Raaid Arshad
Author-email: raaid@protonmail.com
Requires-Python: >=3.9,<3.10
Classifier: Programming Language :: Python :: 3
Classifier: Programming Language :: Python :: 3.9
Requires-Dist: boto3 (==1.26.13)
Requires-Dist: boto3-stubs[ssm] (==1.26.13)
Requires-Dist: psycopg2 (==2.9.5)
Requires-Dist: sqlmodel (==0.0.8)
Project-URL: Repository, https://github.com/LocalAtBrown/ata-models
